{"Titles":{"0":"Cloud Solutions Architect","1":"Machine Learning Engineer","2":"Big Data Machine Learning Engineer","3":"Solution Engineer - State and Local Government","4":"Reliability Mechanical Engineer","5":"Software Engineer, Mental Health Incubator","6":"Data Science Machine Learning Lead","7":"USARPAC G2 Systems Engineer and Data Scientist","8":"HQ INDOPACOM J2 Systems Engineer\/Data Scientist","9":"Technical Lead","10":"Systems Engineer Lead"},"Companies":{"0":"Pythian","1":"Integrity Applications Incorporated","2":"Research Innovations Inc","3":"Esri","4":"Par Hawaii Inc.","5":"Ignite Mental Health","6":"Booz Allen Hamilton","7":"Mitre Corporation","8":"Mitre Corporation","9":"Research Innovations Inc","10":"Alion Science and Technology"},"Cities":{"0":"United States","1":"K\u012bhei","2":"Honolulu","3":"Honolulu","4":"Kapolei","5":"Honolulu","6":"Honolulu","7":"Honolulu","8":"Honolulu","9":"Honolulu","10":"Honolulu"},"States":{"0":"None","1":"HI","2":"HI","3":"HI","4":"HI","5":"HI","6":"HI","7":"HI","8":"HI","9":"HI","10":"HI"}}